{
  "server": {
    "labels": "web",
    "tls": false,
    "client_id": "2222-0000-0000-0000",
    "client_secret": "2222-0000-0000-0001",
    "folder": "bin"
  },
  "logging": {
    "reporters": {
      "myConsoleReporter": [
        {
          "module": "good-squeeze",
          "name": "Squeeze",
          "args": [
            {
              "log": "*",
              "response": "*"
            }
          ]
        },
        {
          "module": "good-console"
        },
        "stdout"
      ]
    }
  },
  "views": {
    "isCached": false
  }
}
